sdypy/__init__.py
sdypy/model/__init__.py
sdypy/model/eigenvalue_solution.py
sdypy/model/beam/beam.py
sdypy/model/mesh/__init__.py
sdypy/model/mesh/mesh_2D.py
sdypy/model/shell/shell.py
sdypy/model/tetrahedron/mass_tet_basis.py
sdypy/model/tetrahedron/tet10.py
sdypy_model-0.1.2.dist-info/METADATA
sdypy_model-0.1.2.dist-info/WHEEL
sdypy_model-0.1.2.dist-info/RECORD
