Metadata-Version: 2.4
Name: sdypy-model
Version: 0.1.2
Summary: System modeling, including lumped mass and FEM.
Project-URL: homepage, https://github.com/sdypy/sdypy-model
Project-URL: documentation, https://github.com/sdypy/sdypy-model
Project-URL: source, https://github.com/sdypy/sdypy-model
Author-email: "Klemen Zaletelj, Janko Slavič et al." <janko.slavic@fs.uni-lj.si>
Maintainer-email: "Klemen Zaletelj, Janko Slavič et al." <klemen.zaletelj@fs.uni-lj.si>
License-Expression: MIT
Keywords: FEM,System model,lumped mass
Classifier: Development Status :: 5 - Production/Stable
Classifier: Intended Audience :: Developers
Classifier: License :: OSI Approved :: MIT License
Classifier: Programming Language :: Python :: 3.10
Classifier: Topic :: Scientific/Engineering
Requires-Python: >=3.10
Requires-Dist: gmsh
Requires-Dist: meshio
Requires-Dist: numpy>=1.14.3
Requires-Dist: pylump
Requires-Dist: pyqt5
Requires-Dist: pyvista
Requires-Dist: pyvistaqt
Requires-Dist: scipy>=1.1.0
Requires-Dist: tqdm>=4.23.4
Provides-Extra: dev
Requires-Dist: build; extra == 'dev'
Requires-Dist: myst-parser; extra == 'dev'
Requires-Dist: pytest; extra == 'dev'
Requires-Dist: sphinx; extra == 'dev'
Requires-Dist: sphinx-book-theme; extra == 'dev'
Requires-Dist: sphinx-copybutton>=0.5.2; extra == 'dev'
Requires-Dist: twine; extra == 'dev'
Requires-Dist: wheel; extra == 'dev'
